cm2metrics/__init__.py
cm2metrics/cm_test.py
cm2metrics/parse_cm.py
cm2metrics-0.1.dist-info/LICENSE
cm2metrics-0.1.dist-info/METADATA
cm2metrics-0.1.dist-info/WHEEL
cm2metrics-0.1.dist-info/top_level.txt
cm2metrics-0.1.dist-info/RECORD
