Metadata-Version: 2.1
Name: cm2metrics
Version: 0.1
Summary: A lightweight package that analyzes multiple metrics directly from confusion matrix efficiently
Home-page: https://github.com/FisherDock/m2metrics
Author: Zhi Liu
Author-email: cowliucn@gmail.com
License: UNKNOWN
Platform: UNKNOWN
Classifier: Programming Language :: Python :: 3
Classifier: Topic :: Scientific/Engineering
Classifier: License :: OSI Approved :: MIT License
Classifier: Operating System :: OS Independent
Requires-Dist: pandas (>=1.0)
